README.rst
setup.py
pelican_jsfiddle/__init__.py
pelican_jsfiddle/jsfiddle.py
pelican_jsfiddle/jsfiddle_tests.py
pelican_jsfiddle.egg-info/PKG-INFO
pelican_jsfiddle.egg-info/SOURCES.txt
pelican_jsfiddle.egg-info/dependency_links.txt
pelican_jsfiddle.egg-info/requires.txt
pelican_jsfiddle.egg-info/top_level.txt