Metadata-Version: 1.1
Name: pelican-jsfiddle
Version: 0.1.0
Summary: Easily embed JSFiddle in your articles
Home-page: https://github.com/if1live/pelican-jsfiddle
Author: libsora
Author-email: libsora25@gmail.com
License: MIT
Download-URL: https://github.com/if1live/pelican-jsfiddle/tarball/0.1.0
Keywords: pelican,jsfiddle,plugin
Platform: UNKNOWN
Classifier: Development Status :: 4 - Beta
Classifier: Operating System :: OS Independent
Classifier: Programming Language :: Python
Classifier: Programming Language :: Python :: 2.6
Classifier: Programming Language :: Python :: 2.7
Classifier: Intended Audience :: Developers
Classifier: License :: OSI Approved :: MIT License
Classifier: Topic :: Internet :: WWW/HTTP
Classifier: Topic :: Software Development :: Libraries :: Python Modules
Classifier: Topic :: Text Processing
